{
  "experiment_name": "agent_run_2",
  "timestamp": "20260708_160649",
  "backbone": "efficientnet_b0",
  "total_training_time_s": 541.8315353393555,
  "epochs_trained": 10,
  "best_val_macro_f1": 0.3660667756335634,
  "test": {
    "loss": 2.985007293262179,
    "accuracy": 0.3523809523809524,
    "macro_f1": 0.34246239987405414,
    "weighted_f1": 0.34246239987405414,
    "per_class": {
      "Accessories": {
        "precision": 0.11864406779661017,
        "recall": 0.1111111111111111,
        "f1-score": 0.11475409836065574,
        "support": 63.0
      },
      "Garment Full body": {
        "precision": 0.30666666666666664,
        "recall": 0.36507936507936506,
        "f1-score": 0.3333333333333333,
        "support": 63.0
      },
      "Garment Lower body": {
        "precision": 0.22641509433962265,
        "recall": 0.19047619047619047,
        "f1-score": 0.20689655172413793,
        "support": 63.0
      },
      "Garment Upper body": {
        "precision": 0.34545454545454546,
        "recall": 0.30158730158730157,
        "f1-score": 0.3220338983050847,
        "support": 63.0
      },
      "Shoes": {
        "precision": 0.684931506849315,
        "recall": 0.7936507936507936,
        "f1-score": 0.7352941176470589,
        "support": 63.0
      }
    },
    "confusion_matrix": [
      [
        7,
        11,
        16,
        13,
        16
      ],
      [
        18,
        23,
        9,
        11,
        2
      ],
      [
        17,
        20,
        12,
        10,
        4
      ],
      [
        14,
        18,
        11,
        19,
        1
      ],
      [
        3,
        3,
        5,
        2,
        50
      ]
    ]
  },
  "history": [
    {
      "epoch": 1,
      "train_loss": 5.958644905090332,
      "train_acc": 0.2,
      "val_loss": 4.847928634522453,
      "val_acc": 0.1619047619047619,
      "val_macro_f1": 0.1475510537269727,
      "val_weighted_f1": 0.1475510537269727,
      "lr": 0.0002926829491861254,
      "epoch_time_s": 50.829450368881226
    },
    {
      "epoch": 2,
      "train_loss": 4.489106101989746,
      "train_acc": 0.22,
      "val_loss": 4.093882554674906,
      "val_acc": 0.2,
      "val_macro_f1": 0.20859061337438378,
      "val_weighted_f1": 0.20859061337438378,
      "lr": 0.0002714480406590546,
      "epoch_time_s": 51.58900594711304
    },
    {
      "epoch": 3,
      "train_loss": 2.6889288806915284,
      "train_acc": 0.44,
      "val_loss": 3.647952883584159,
      "val_acc": 0.23809523809523808,
      "val_macro_f1": 0.2461093085543581,
      "val_weighted_f1": 0.24610930855435806,
      "lr": 0.0002383738952177247,
      "epoch_time_s": 50.5313720703125
    },
    {
      "epoch": 4,
      "train_loss": 3.6105336475372316,
      "train_acc": 0.34,
      "val_loss": 3.390956774212065,
      "val_acc": 0.2761904761904762,
      "val_macro_f1": 0.2750292271871303,
      "val_weighted_f1": 0.2750292271871303,
      "lr": 0.0001966980406590546,
      "epoch_time_s": 51.88798189163208
    },
    {
      "epoch": 5,
      "train_loss": 2.244299736022949,
      "train_acc": 0.52,
      "val_loss": 3.228503537934924,
      "val_acc": 0.33015873015873015,
      "val_macro_f1": 0.32885119618180364,
      "val_weighted_f1": 0.3288511961818037,
      "lr": 0.00015049999999999997,
      "epoch_time_s": 49.54139518737793
    },
    {
      "epoch": 6,
      "train_loss": 2.759575061798096,
      "train_acc": 0.4,
      "val_loss": 3.1340019895916895,
      "val_acc": 0.33015873015873015,
      "val_macro_f1": 0.3255890907294119,
      "val_weighted_f1": 0.3255890907294119,
      "lr": 0.00010430195934094535,
      "epoch_time_s": 53.31022071838379
    },
    {
      "epoch": 7,
      "train_loss": 1.6965198135375976,
      "train_acc": 0.5,
      "val_loss": 3.048674227888622,
      "val_acc": 0.3333333333333333,
      "val_macro_f1": 0.32965981090628754,
      "val_weighted_f1": 0.32965981090628754,
      "lr": 6.262610478227527e-05,
      "epoch_time_s": 50.872026443481445
    },
    {
      "epoch": 8,
      "train_loss": 1.5607937860488892,
      "train_acc": 0.58,
      "val_loss": 2.9869016760871525,
      "val_acc": 0.346031746031746,
      "val_macro_f1": 0.34406244252730456,
      "val_weighted_f1": 0.3440624425273046,
      "lr": 2.955195934094537e-05,
      "epoch_time_s": 50.34380531311035
    },
    {
      "epoch": 9,
      "train_loss": 1.4975745344161988,
      "train_acc": 0.54,
      "val_loss": 2.9026107723750765,
      "val_acc": 0.35873015873015873,
      "val_macro_f1": 0.35846774428425804,
      "val_weighted_f1": 0.35846774428425804,
      "lr": 8.317050813874547e-06,
      "epoch_time_s": 50.11956572532654
    },
    {
      "epoch": 10,
      "train_loss": 1.1761796474456787,
      "train_acc": 0.58,
      "val_loss": 2.9016768122476244,
      "val_acc": 0.36507936507936506,
      "val_macro_f1": 0.3660667756335634,
      "val_weighted_f1": 0.36606677563356343,
      "lr": 1e-06,
      "epoch_time_s": 51.70368719100952
    }
  ],
  "config": {
    "experiment": {
      "name": "agent_run_2",
      "notes": "Workflow 1 baseline \u2014 human-prepared data, agent trains. No advanced augmentations reserved for agent."
    },
    "paths": {
      "data_dir": "data/sample",
      "class_weights": "data/class_weights.json",
      "class_mapping": "data/class_mapping.json",
      "experiment_dir": "experiments",
      "output_dir": "experiments/run_2"
    },
    "model": {
      "backbone": "efficientnet_b0",
      "pretrained": true,
      "checkpoint": null,
      "image_size": 224,
      "dropout": 0.5
    },
    "training": {
      "epochs": 10,
      "batch_size": 32,
      "num_workers": 0,
      "mixed_precision": true,
      "early_stopping_patience": 5,
      "early_stopping_min_delta": 0.001,
      "max_samples_per_class": 10
    },
    "optimizer": {
      "type": "adamw",
      "lr": 0.0003,
      "weight_decay": 0.01,
      "momentum": 0.9
    },
    "scheduler": {
      "type": "cosine",
      "min_lr": 1e-06,
      "step_size": 7,
      "gamma": 0.1,
      "warmup_epochs": 0
    },
    "loss": {
      "type": "weighted_ce",
      "label_smoothing": 0.0,
      "focal_gamma": 2.0,
      "use_class_weights": true
    },
    "sampler": {
      "use_weighted": true
    },
    "augmentations": {
      "random_resized_crop": true,
      "random_horizontal_flip": true,
      "color_jitter": true,
      "color_jitter_brightness": 0.2,
      "color_jitter_contrast": 0.2,
      "color_jitter_saturation": 0.2,
      "color_jitter_hue": 0.05,
      "random_erasing": true,
      "random_erasing_prob": 0.5,
      "mixup": false,
      "mixup_alpha": 0.4,
      "cutmix": false,
      "cutmix_alpha": 1.0,
      "randaugment": true,
      "randaugment_n": 2,
      "randaugment_m": 9,
      "autoaugment": false
    }
  }
}